{
  "user_id": "usr_000035",
  "window_days": 180,
  "persona": {
    "persona_id": "subscription_heavy",
    "window_days": 180,
    "assigned_at": "2025-11-04T15:31:06.288130",
    "criteria_met": {
      "persona": "subscription_heavy",
      "recurring_merchant_count": 5,
      "monthly_recurring_spend": 134.95,
      "subscription_share_pct": 3.1,
      "matched_on": [
        "recurring_merchants_gte_3",
        "monthly_recurring_gte_50"
      ]
    }
  },
  "signals": {
    "subscription": {
      "recurring_merchant_count": 5,
      "monthly_recurring_spend": 134.95,
      "subscription_share_pct": 3.1,
      "computed_at": "2025-11-04T15:31:06.275982"
    },
    "savings": {
      "savings_net_inflow": 872.0,
      "savings_growth_rate_pct": 6.12,
      "emergency_fund_months": 7.15,
      "computed_at": "2025-11-04T15:31:06.279270"
    },
    "credit": {
      "credit_utilization_max_pct": 15.0,
      "credit_utilization_avg_pct": 12.5,
      "credit_util_flag_30": false,
      "credit_util_flag_50": false,
      "credit_util_flag_80": false,
      "has_interest_charges": false,
      "has_minimum_payment_only": false,
      "is_overdue": false,
      "computed_at": "2025-11-04T15:31:06.282626"
    },
    "income": {
      "payroll_deposit_count": 6,
      "median_pay_gap_days": 30.0,
      "pay_gap_variability": 0.0,
      "avg_payroll_amount": 12718.5,
      "cashflow_buffer_months": 1.07,
      "computed_at": "2025-11-04T15:31:06.286017"
    }
  },
  "signal_count": 4,
  "recommendations": [
    {
      "id": 238,
      "item_type": "education",
      "title": "The Subscription Audit Checklist",
      "rationale": "You have 5 recurring subscriptions. totaling about $134.95/month. Consider this resource to help optimize your subscriptions.",
      "persona_id": "subscription_heavy",
      "status": "pending",
      "eligibility_flags": {
        "tone_check": "passed"
      },
      "disclosure": "This is educational content, not financial advice. Consult a licensed advisor for personalized guidance.",
      "created_at": "2025-11-04T15:31:06.290798"
    },
    {
      "id": 239,
      "item_type": "education",
      "title": "Negotiating Lower Bills: Scripts That Work",
      "rationale": "You have 5 recurring subscriptions. totaling about $134.95/month. Consider this resource to help optimize your subscriptions.",
      "persona_id": "subscription_heavy",
      "status": "pending",
      "eligibility_flags": {
        "tone_check": "passed"
      },
      "disclosure": "This is educational content, not financial advice. Consult a licensed advisor for personalized guidance.",
      "created_at": "2025-11-04T15:31:06.290800"
    },
    {
      "id": 240,
      "item_type": "education",
      "title": "Setting Up Bill Alerts and Reminders",
      "rationale": "You have 5 recurring subscriptions. totaling about $134.95/month. Consider this resource to help optimize your subscriptions.",
      "persona_id": "subscription_heavy",
      "status": "pending",
      "eligibility_flags": {
        "tone_check": "passed"
      },
      "disclosure": "This is educational content, not financial advice. Consult a licensed advisor for personalized guidance.",
      "created_at": "2025-11-04T15:31:06.290800"
    },
    {
      "id": 241,
      "item_type": "offer",
      "title": "Budgeting App Premium - 3 Months Free",
      "rationale": "You have 5 recurring subscriptions. totaling about $134.95/month. Consider this resource to help optimize your subscriptions.",
      "persona_id": "subscription_heavy",
      "status": "pending",
      "eligibility_flags": {
        "eligible": true,
        "reason": "No eligibility restrictions",
        "tone_check": "passed"
      },
      "disclosure": "This is educational content, not financial advice. Consult a licensed advisor for personalized guidance.",
      "created_at": "2025-11-04T15:31:06.290800"
    },
    {
      "id": 242,
      "item_type": "offer",
      "title": "Subscription Manager Tool - Free Tier",
      "rationale": "You have 5 recurring subscriptions. totaling about $134.95/month. Consider this resource to help optimize your subscriptions.",
      "persona_id": "subscription_heavy",
      "status": "pending",
      "eligibility_flags": {
        "eligible": true,
        "reason": "No eligibility restrictions",
        "tone_check": "passed"
      },
      "disclosure": "This is educational content, not financial advice. Consult a licensed advisor for personalized guidance.",
      "created_at": "2025-11-04T15:31:06.290801"
    },
    {
      "id": 243,
      "item_type": "offer",
      "title": "Bill Negotiation Service - No Fee Unless We Save You Money",
      "rationale": "You have 5 recurring subscriptions. totaling about $134.95/month. Consider this resource to help optimize your subscriptions.",
      "persona_id": "subscription_heavy",
      "status": "pending",
      "eligibility_flags": {
        "eligible": true,
        "reason": "Meets all eligibility criteria",
        "tone_check": "passed"
      },
      "disclosure": "This is educational content, not financial advice. Consult a licensed advisor for personalized guidance.",
      "created_at": "2025-11-04T15:31:06.290801"
    }
  ],
  "recommendation_count": 6,
  "trace_generated_at": "2025-11-04T15:31:14.783291"
}